planemo/__init__.py
planemo/autoupdate.py
planemo/ci.py
planemo/cli.py
planemo/conda.py
planemo/config.py
planemo/context.py
planemo/deps.py
planemo/docker.py
planemo/exit_codes.py
planemo/git.py
planemo/github_util.py
planemo/glob.py
planemo/io.py
planemo/lint.py
planemo/mulled.py
planemo/network_util.py
planemo/options.py
planemo/runnable.py
planemo/runnable_resolve.py
planemo/shed_lint.py
planemo/templates.py
planemo/tool_builder.py
planemo/tool_lint.py
planemo/tools.py
planemo/virtualenv.py
planemo/workflow_lint.py
planemo/autopygen/__init__.py
planemo/autopygen/argument_parser_conversion.py
planemo/autopygen/param_info.py
planemo/autopygen/commands/__init__.py
planemo/autopygen/commands/command_utils.py
planemo/autopygen/source_file_parsing/__init__.py
planemo/autopygen/source_file_parsing/constants.py
planemo/autopygen/source_file_parsing/decoy_parser.py
planemo/autopygen/source_file_parsing/local_module_parsing.py
planemo/autopygen/source_file_parsing/parser_discovery_and_init.py
planemo/autopygen/source_file_parsing/parsing_commons.py
planemo/autopygen/source_file_parsing/parsing_exceptions.py
planemo/autopygen/source_file_parsing/unknown_names_discovery.py
planemo/autopygen/xml/__init__.py
planemo/autopygen/xml/xml_utils.py
planemo/commands/__init__.py
planemo/commands/cmd_autoupdate.py
planemo/commands/cmd_ci_find_repos.py
planemo/commands/cmd_ci_find_tools.py
planemo/commands/cmd_ci_setup.py
planemo/commands/cmd_clone.py
planemo/commands/cmd_conda_build.py
planemo/commands/cmd_conda_env.py
planemo/commands/cmd_conda_init.py
planemo/commands/cmd_conda_install.py
planemo/commands/cmd_conda_search.py
planemo/commands/cmd_config_init.py
planemo/commands/cmd_container_register.py
planemo/commands/cmd_create_alias.py
planemo/commands/cmd_create_gist.py
planemo/commands/cmd_database_create.py
planemo/commands/cmd_database_delete.py
planemo/commands/cmd_database_list.py
planemo/commands/cmd_delete_alias.py
planemo/commands/cmd_docker_build.py
planemo-0.75.35.dist-info/licenses/LICENSE
planemo-0.75.35.dist-info/METADATA
planemo-0.75.35.dist-info/WHEEL
planemo-0.75.35.dist-info/entry_points.txt
planemo-0.75.35.dist-info/top_level.txt
planemo-0.75.35.dist-info/RECORD
