Metadata-Version: 2.4
Name: planemo
Version: 0.75.35
Summary: Command-line utilities to assist in building tools for the Galaxy project (http://galaxyproject.org/).
Author-email: Galaxy Project and Community <galaxy-committers@lists.galaxyproject.org>
License-Expression: MIT
Classifier: Development Status :: 5 - Production/Stable
Classifier: Intended Audience :: Developers
Classifier: Environment :: Console
Classifier: Operating System :: POSIX
Classifier: Topic :: Software Development
Classifier: Topic :: Software Development :: Code Generators
Classifier: Topic :: Software Development :: Testing
Classifier: Natural Language :: English
Classifier: Programming Language :: Python :: 3
Classifier: Programming Language :: Python :: 3.7
Classifier: Programming Language :: Python :: 3.8
Classifier: Programming Language :: Python :: 3.9
Classifier: Programming Language :: Python :: 3.10
Classifier: Programming Language :: Python :: 3.11
Classifier: Programming Language :: Python :: 3.12
License-File: LICENSE
Requires-Dist: allure-python-commons
Requires-Dist: bioblend>=1.6.0
Requires-Dist: click!=8.0.2
Requires-Dist: cryptography>=46.0.3
Requires-Dist: cwltool>=1.0.20191225192155
Requires-Dist: ephemeris>=0.10.3
Requires-Dist: galaxy-job-config-init>=0.1.3
Requires-Dist: galaxy-tool-util[edam,extended-assertions]<26.0,>=25.1
Requires-Dist: galaxy-util[template]<26.0,>=24.1
Requires-Dist: glob2
Requires-Dist: gxformat2>=0.14.0
Requires-Dist: h5py
Requires-Dist: jinja2
Requires-Dist: lxml
Requires-Dist: oyaml
Requires-Dist: pathvalidate
Requires-Dist: pyyaml
Requires-Dist: ruamel.yaml
Requires-Dist: virtualenv
Requires-Dist: stdlib-list; python_version < "3.10"
Requires-Dist: tabulate
Dynamic: license-file
